MilPython
