Metadata-Version: 2.1
Name: milpython
Version: 0.5.7
Summary: Framework for building MILP optimizations for time series with gurobipy
Home-page: https://github.com/hanneshanse/MilPython
Author: Hannes Hanse
Author-email: hannes.hanse@tu-clausthal.de
License: MIT
Keywords: milp,time series,optimization,gurobi,gurobipy
Classifier: Programming Language :: Python :: 3
Classifier: License :: OSI Approved :: MIT License
Classifier: Operating System :: OS Independent
License-File: LICENSE.txt
Requires-Dist: scipy
Requires-Dist: gurobipy
Requires-Dist: numpy
Requires-Dist: matplotlib
